winpdb_legacy.py
winpdb-1.4.9.2.dist-info/LICENSE.txt
winpdb-1.4.9.2.dist-info/METADATA
winpdb-1.4.9.2.dist-info/WHEEL
winpdb-1.4.9.2.dist-info/entry_points.txt
winpdb-1.4.9.2.dist-info/top_level.txt
winpdb-1.4.9.2.dist-info/RECORD
